{
  "$schema": "https://developer.microsoft.com/json-schemas/fabric/item/report/definition/visualContainer/2.4.0/schema.json",
  "name": "d1a3b827940e56cf",
  "position": {
    "tabOrder": 3132,
    "y": 628,
    "width": 28,
    "x": 304,
    "height": 25,
    "z": 3132
  },
  "visual": {
    "visualType": "image",
    "objects": {
      "image": [
        {
          "properties": {
            "sourceFile": {
              "image": {
                "url": {
                  "expr": {
                    "ResourcePackageItem": {
                      "PackageType": 1,
                      "PackageName": "RegisteredResources",
                      "ItemName": "ic_fluent_settings_24_filled102618747069814_red.svg"
                    }
                  }
                },
                "name": {
                  "expr": {
                    "Literal": {
                      "Value": "'ic_fluent_settings_24_filled102618747069814_red.svg'"
                    }
                  }
                }
              }
            }
          }
        }
      ]
    },
    "drillFilterOtherVisuals": true
  }
}