{
  "$schema": "https://developer.microsoft.com/json-schemas/fabric/item/report/definition/visualContainer/2.4.0/schema.json",
  "name": "d10bec57683fa249",
  "position": {
    "tabOrder": 2133,
    "y": 495,
    "width": 28,
    "x": 332,
    "height": 25,
    "z": 2133
  },
  "visual": {
    "visualType": "image",
    "objects": {
      "image": [
        {
          "properties": {
            "sourceFile": {
              "image": {
                "url": {
                  "expr": {
                    "ResourcePackageItem": {
                      "PackageType": 1,
                      "PackageName": "RegisteredResources",
                      "ItemName": "ic_fluent_search_24_filled9130668959125045_blue.svg"
                    }
                  }
                },
                "name": {
                  "expr": {
                    "Literal": {
                      "Value": "'ic_fluent_search_24_filled9130668959125045_blue.svg'"
                    }
                  }
                }
              }
            }
          }
        }
      ]
    },
    "drillFilterOtherVisuals": true
  }
}