{
  "$schema": "https://developer.microsoft.com/json-schemas/fabric/item/report/definition/visualContainer/2.4.0/schema.json",
  "name": "1be690c354728afd",
  "position": {
    "tabOrder": 2011,
    "y": 395,
    "width": 28,
    "x": 500,
    "height": 25,
    "z": 2011
  },
  "visual": {
    "visualType": "image",
    "objects": {
      "image": [
        {
          "properties": {
            "sourceFile": {
              "image": {
                "url": {
                  "expr": {
                    "ResourcePackageItem": {
                      "PackageType": 1,
                      "PackageName": "RegisteredResources",
                      "ItemName": "ic_fluent_dismiss_24_filled5229979352940058_blue.svg"
                    }
                  }
                },
                "name": {
                  "expr": {
                    "Literal": {
                      "Value": "'ic_fluent_dismiss_24_filled5229979352940058_blue.svg'"
                    }
                  }
                }
              }
            }
          }
        }
      ]
    },
    "drillFilterOtherVisuals": true
  }
}